pycony/__init__.py
pycony-0.1.3.dist-info/licenses/LICENSE
pycony-0.1.3.dist-info/METADATA
pycony-0.1.3.dist-info/WHEEL
pycony-0.1.3.dist-info/top_level.txt
pycony-0.1.3.dist-info/RECORD
